finam_graph/__init__.py
finam_graph/_version.py
finam_graph/diagram.py
finam_graph/graph.py
finam_graph-0.1.0.dist-info/METADATA
finam_graph-0.1.0.dist-info/WHEEL
finam_graph-0.1.0.dist-info/licenses/AUTHORS.md
finam_graph-0.1.0.dist-info/licenses/COPYING.LESSER
finam_graph-0.1.0.dist-info/licenses/LICENSE.md
finam_graph-0.1.0.dist-info/RECORD
